upside_down_rl/__init__.py
upside_down_rl/cartpole.py
upside_down_rl/gym_model.py
upside_down_rl/lander.py
upside_down_rl/udrl.py
upside_down_rl/utils.py
upside_down_rl-0.1.0.dist-info/entry_points.txt
upside_down_rl-0.1.0.dist-info/WHEEL
upside_down_rl-0.1.0.dist-info/METADATA
upside_down_rl-0.1.0.dist-info/RECORD
