Metadata-Version: 2.1
Name: upside-down-rl
Version: 0.1.0
Summary: 
Author: Richard Weiss
Author-email: richardweiss@richardweiss.org
Requires-Python: >=3.7,<4.0
Classifier: Programming Language :: Python :: 3
Classifier: Programming Language :: Python :: 3.7
Classifier: Programming Language :: Python :: 3.8
Requires-Dist: attrs (>=19.3.0,<20.0.0)
Requires-Dist: grappa (>=0.1.10,<0.2.0)
Requires-Dist: gym[box2d] (>=0.15.4,<0.16.0)
Requires-Dist: lz4 (>=3.0.2,<4.0.0)
Requires-Dist: minio (>=5.0.6,<6.0.0)
Requires-Dist: pytorch-ignite (>=0.2.1,<0.3.0)
Requires-Dist: scikit-learn (>=0.22.1,<0.23.0)
Requires-Dist: sortedcontainers (>=2.1.0,<3.0.0)
Requires-Dist: tensorboardX (>=2.0,<3.0)
Requires-Dist: torch (>=1.3.1,<2.0.0)
Requires-Dist: tqdm (>=4.41.1,<5.0.0)
